LICENSE.md
README.md
listy.py
test_listy.py
slice_ref-0.0.2.dist-info/LICENSE.md
slice_ref-0.0.2.dist-info/WHEEL
slice_ref-0.0.2.dist-info/METADATA
slice_ref-0.0.2.dist-info/RECORD
