Metadata-Version: 2.1
Name: slice-ref
Version: 0.0.2
Summary: Reference implementation of Python's list slicing resolution
Home-page: https://github.com/Honno/py-slicing-reference
License: BSD-3-Clause
Author: Matthew Barber
Author-email: quitesimplymatt@gmail.com
Requires-Python: >=3.8,<4.0
Classifier: License :: OSI Approved :: BSD License
Classifier: Programming Language :: Python :: 3
Classifier: Programming Language :: Python :: 3.8
Classifier: Programming Language :: Python :: 3.9
Project-URL: Repository, https://github.com/Honno/py-slicing-reference
